odoo/addons/sale_commission_settlement_report/README.rst
odoo/addons/sale_commission_settlement_report/__init__.py
odoo/addons/sale_commission_settlement_report/__manifest__.py
odoo/addons/sale_commission_settlement_report/i18n/it.po
odoo/addons/sale_commission_settlement_report/i18n/sale_commission_settlement_report.pot
odoo/addons/sale_commission_settlement_report/models/__init__.py
odoo/addons/sale_commission_settlement_report/models/res_company.py
odoo/addons/sale_commission_settlement_report/models/res_config_settings.py
odoo/addons/sale_commission_settlement_report/models/sale_commission_settlement.py
odoo/addons/sale_commission_settlement_report/models/sale_commission_settlement_line.py
odoo/addons/sale_commission_settlement_report/readme/CONFIGURE.rst
odoo/addons/sale_commission_settlement_report/readme/DESCRIPTION.rst
odoo/addons/sale_commission_settlement_report/static/description/icon.png
odoo/addons/sale_commission_settlement_report/static/description/index.html
odoo/addons/sale_commission_settlement_report/views/report_settlement_templates.xml
odoo/addons/sale_commission_settlement_report/views/res_config_settings_view.xml
odoo/addons/sale_commission_settlement_report/views/sale_commission_settlement_view.xml
odoo14_addon_sale_commission_settlement_report-14.0.1.0.1.dev4.dist-info/METADATA
odoo14_addon_sale_commission_settlement_report-14.0.1.0.1.dev4.dist-info/WHEEL
odoo14_addon_sale_commission_settlement_report-14.0.1.0.1.dev4.dist-info/top_level.txt
odoo14_addon_sale_commission_settlement_report-14.0.1.0.1.dev4.dist-info/RECORD
